steer/__init__.py
steer/__main__.py
steer/cli.py
steer/models.py
steer/schema.py
python_steer-0.2.0.dist-info/METADATA
python_steer-0.2.0.dist-info/WHEEL
python_steer-0.2.0.dist-info/entry_points.txt
python_steer-0.2.0.dist-info/RECORD
