Metadata-Version: 2.1
Name: python-steer
Version: 0.2.0
Summary: A tool to help you write JSON and YAML files from JSON schemas
Author: José Coelho
Author-email: 16445494+jcoelho93@users.noreply.github.com
Requires-Python: >=3.12,<4.0
Classifier: Programming Language :: Python :: 3
Classifier: Programming Language :: Python :: 3.12
Requires-Dist: click (==8.1.7)
Requires-Dist: jsonpath-ng (>=1.6.1,<2.0.0)
Requires-Dist: pydantic (>=2.7.1,<3.0.0)
Requires-Dist: pyyaml (>=6.0.1,<7.0.0)
Requires-Dist: questionary (>=2.0.1,<3.0.0)
Project-URL: Bug Tracker, https://github.com/jcoelho93/steer/issues
